mcp_brevo/__init__.py
mcp_brevo/config.py
mcp_brevo/main.py
mcp_brevo/mcp.py
mcp_brevo/tools/__init__.py
mcp_brevo/tools/account.py
mcp_brevo/tools/analytics.py
mcp_brevo/tools/campaigns.py
mcp_brevo/tools/contacts.py
mcp_brevo/tools/emails.py
mcp_brevo/tools/lists.py
mcp_brevo/tools/sms.py
mcp_brevo/tools/templates.py
mcp_brevo/utils/__init__.py
mcp_brevo/utils/api_client.py
mcp_brevo/utils/error_handlers.py
mcp_brevo-0.2.2.dist-info/METADATA
mcp_brevo-0.2.2.dist-info/WHEEL
mcp_brevo-0.2.2.dist-info/entry_points.txt
mcp_brevo-0.2.2.dist-info/top_level.txt
mcp_brevo-0.2.2.dist-info/RECORD
