Metadata-Version: 2.4
Name: mcp-brevo
Version: 0.2.2
Summary: Brevo MCP for managing contacts, campaigns, emails, and more
Author-email: Antoine Picolet <antoine.picolet@example.com>
Project-URL: Homepage, https://github.com/yourusername/mcp-brevo
Project-URL: Bug Tracker, https://github.com/yourusername/mcp-brevo/issues
Classifier: Development Status :: 4 - Beta
Classifier: Intended Audience :: Developers
Classifier: Programming Language :: Python :: 3
Classifier: Programming Language :: Python :: 3.12
Classifier: License :: OSI Approved :: MIT License
Requires-Python: >=3.12
Requires-Dist: httpx>=0.28.1
Requires-Dist: mcp[cli]>=1.8.1
Requires-Dist: brevo-python>=1.1.2
Requires-Dist: requests>=2.31.0
